ohpygossh-0.0.15.dist-info/top_level.txt
ohpygossh-0.0.15.dist-info/RECORD
ohpygossh-0.0.15.dist-info/METADATA
ohpygossh-0.0.15.dist-info/WHEEL
ohpygossh/gohpygossh.c
ohpygossh/build.py
ohpygossh/__init__.py
ohpygossh/gohpygossh.go
ohpygossh/gohpygossh.py
ohpygossh/_gohpygossh.cpython-311-aarch64-linux-musl.h
ohpygossh/go.py
ohpygossh/_gohpygossh.cpython-311-aarch64-linux-musl.so
ohpygossh/gohpygossh_go.h
