Metadata-Version: 2.4
Name: ohpygossh
Version: 0.0.15
Summary: A project to create a new cross-platform SSH wheel for Python.
Home-page: https://github.com/b-long/ohpygossh
Author: b-long
Classifier: Programming Language :: Python :: 3
Classifier: License :: OSI Approved :: MIT License
Classifier: Operating System :: OS Independent
Dynamic: author
Dynamic: classifier
Dynamic: description
Dynamic: description-content-type
Dynamic: home-page
Dynamic: summary
